[
  {
    "_id": "65bd7f0c5aa3e4f5b5ac908f",
    "vid": 1,
    "tid": 393210,
    "badge": "https://lain.bgm.tv/pic/photo/l/32/c1/437960_T2Mmm.jpg",
    "blogs": [
      331172,
      330877,
      331579,
      331169,
      330987,
      332341,
      329664,
      329818,
      331524,
      328616,
      327361
    ],
    "note": "本文已收录于「半月刊Feb2024上」"
  },
  {
    "_id": "65be8c2432d552adb8d0bb33",
    "vid": 10001,
    "tid": 393586,
    "badge": "https://lain.bgm.tv/pic/photo/l/32/c1/437960_ub1zY.jpg",
    "blogs": [
      330877,
      331524,
      298216,
      296238,
      296237,
      296236,
      299725,
      299724,
      302719,
      320595,
      315281,
      296196,
      308051,
      325604,
      333405,
      333083,
      332912,
      334440,
      333503
    ],
    "note": "本文已收录于「访谈合集」"
  },
  {
    "_id": "65c16e418607d3fc996f204d",
    "vid": 10002,
    "tid": 393585,
    "badge": "https://lain.bgm.tv/pic/photo/l/32/c1/437960_XOxHU.jpg",
    "blogs": [
      323452,
      322083,
      319520,
      315240,
      310828,
      307246,
      337125,
      337558
    ],
    "note": "本文已收录于「Mechademia译文合集」"
  },
  {
    "_id": "65c17f868607d3fc996f204f",
    "vid": 10003,
    "tid": 393584,
    "badge": "https://lain.bgm.tv/pic/photo/l/32/c1/437960_99f8F.jpg",
    "blogs": [
      324975,
      313741,
      282025,
      296238,
      296237,
      298216,
      296236,
      323525,
      323524,
      334256
    ],
    "note": "本文已收录于「押井守合集」"
  },
  {
    "_id": "65c3c9e216fd847379bc20fe",
    "vid": 2,
    "tid": 393771,
    "badge": "https://lain.bgm.tv/pic/photo/l/32/c1/437960_T2Mmm.jpg",
    "blogs": [
      332367,
      332828,
      333086,
      333405,
      333083,
      332912,
      300848,
      301991,
      320794,
      304102
    ],
    "note": "本文已收录于「半月刊Feb2024下」"
  },
  {
    "_id": "65c94109d9d2f5e412cb4d34",
    "vid": 10004,
    "tid": 393587,
    "badge": "https://lain.bgm.tv/pic/photo/l/32/c1/437960_da2ve.jpg",
    "blogs": [
      333157,
      306137,
      271929,
      272831,
      307761
    ],
    "note": "本文已收录于「拉片合集」"
  },
  {
    "_id": "65e340dd5aa2fb9fd45e694c",
    "vid": 3,
    "tid": 394414,
    "badge": "https://lain.bgm.tv/pic/photo/l/32/c1/437960_T2Mmm.jpg",
    "note": "本文已收录于「半月刊Mar2024上」",
    "blogs": [
      334256,
      333499,
      334440,
      295447,
      333614,
      330997,
      334492,
      334446,
      333750,
      307878,
      319325,
      279460
    ]
  },
  {
    "_id": "65f71fa7d618b521f1f73ce4",
    "vid": 4,
    "tid": 395165,
    "badge": "https://lain.bgm.tv/pic/photo/l/32/c1/437960_T2Mmm.jpg",
    "note": "本文已收录于「半月刊Mar2024下」",
    "blogs": [
      334703,
      324975,
      319403,
      309989,
      335126,
      44534,
      281775,
      310029,
      322769,
      323980,
      329244,
      334595
    ]
  },
  {
    "_id": "6603eaea84f9c68f60a741b7",
    "vid": 5,
    "tid": 395728,
    "badge": "https://lain.bgm.tv/pic/photo/l/32/c1/437960_T2Mmm.jpg",
    "note": "本文已收录于「半月刊April2024上」",
    "blogs": [
      335654,
      315240,
      300696,
      274874,
      335476,
      335869,
      335734,
      310076,
      313299,
      310447,
      328850,
      295895
    ]
  },
  {
    "_id": "661eb683e326ebc1d5157748",
    "vid": 6,
    "tid": 396952,
    "badge": "https://lain.bgm.tv/pic/photo/l/32/c1/437960_T2Mmm.jpg",
    "note": "本文已收录于「半月刊April2024下」",
    "blogs": [
      336578,
      337030,
      336808,
      336686,
      337125,
      337208,
      322559,
      337190,
      336459,
      336554,
      337102,
      336494,
      336752
    ]
  },
  {
    "_id": "6632ecb152b04cd9bce22502",
    "vid": 7,
    "tid": 397786,
    "badge": "https://lain.bgm.tv/pic/photo/l/32/c1/437960_T2Mmm.jpg",
    "note": "本文已收录于「半月刊May2024上」",
    "blogs": [
      337362,
      310091,
      281920,
      273636,
      310920,
      337169,
      337170,
      336284,
      313774,
      305317,
      303484,
      285621,
      313527,
      297408
    ]
  },
  {
    "_id": "6654fe47950a216371e3b93d",
    "vid": 8,
    "tid": 399124,
    "badge": "https://lain.bgm.tv/pic/photo/l/32/c1/437960_T2Mmm.jpg",
    "note": "本文已收录于「半月刊Jun2024上」",
    "blogs": [
      337974,
      310061,
      313579,
      338215,
      307531,
      328867,
      282050,
      281781,
      324089,
      307023,
      310828,
      294609,
      307167,
      325521,
      272831,
      308208
    ]
  },
  {
    "_id": "66bdc2b66504801b064510fb",
    "vid": 10,
    "tid": 403766,
    "badge": "https://lain.bgm.tv/pic/photo/l/32/c1/437960_T2Mmm.jpg",
    "note": "本文已收录于「半月刊Aug2024下」",
    "blogs": [
      339940,
      338676,
      47028,
      341761,
      340267,
      341836,
      341609,
      342399,
      342038,
      336920,
      340510,
      341330,
      340677
    ]
  },
  {
    "_id": "66f11c6d3509ae160a6e4e7f",
    "vid": 11,
    "tid": 405929,
    "badge": "https://lain.bgm.tv/pic/photo/l/32/c1/437960_T2Mmm.jpg",
    "note": "本文已收录于「半月刊Sept2024下」",
    "blogs": [
      312491,
      3088,
      326128,
      343830,
      343607,
      344278,
      313051,
      319069,
      319520,
      337968,
      339223,
      301038
    ]
  },
  {
    "_id": "67029aafc881b3e93e240d9b",
    "vid": 9,
    "tid": 406809,
    "badge": "https://lain.bgm.tv/pic/photo/l/32/c1/437960_T2Mmm.jpg",
    "note": "本文已收录于「半月刊Aug2024上」",
    "blogs": [
      342323,
      344319,
      306210,
      305261,
      272903,
      339509,
      302802,
      296693,
      312971,
      1640,
      324357,
      318379
    ]
  },
  {
    "_id": "672857f1db978da9ce62fa85",
    "vid": 10004,
    "tid": 408852,
    "badge": "https://lain.bgm.tv/pic/photo/l/32/c1/437960_eDOSC.jpg",
    "blogs": [
      330185,
      331336,
      333405,
      334615,
      336211,
      337242,
      337836,
      338745,
      338323,
      338504,
      338505,
      338745,
      338749,
      339083,
      339086,
      339656,
      340621,
      340972,
      342574,
      344118,
      344494,
      344835,
      336843,
      337251,
      337586,
      337922,
      338157,
      338413,
      338636,
      338853,
      338844,
      339404,
      339117,
      338890,
      339687,
      339762,
      339989,
      340677,
      341240,
      339623,
      341809,
      345749,
      339407
    ],
    "note": "本文已收录于「Girls Band Cry 呐喊！少女乐队 访谈&资讯&日志」"
  },
  {
    "_id": "67285a64db978da9ce62fa86",
    "vid": 12,
    "tid": 408160,
    "badge": "https://lain.bgm.tv/pic/photo/l/32/c1/437960_T2Mmm.jpg",
    "note": "本文已收录于「半月刊Oct2024上」",
    "blogs": [
      344668,
      344745,
      344672,
      343417,
      337198,
      308534,
      279702,
      299286,
      55273,
      343213,
      283361,
      314256,
      339743
    ]
  },
  {
    "_id": "674e1fc7fa8e90dfd96b8230",
    "vid": 13,
    "tid": 410993,
    "badge": "https://lain.bgm.tv/pic/photo/l/32/c1/437960_T2Mmm.jpg",
    "note": "本文已收录于「半月刊Nov2024上」",
    "blogs": [
      345403,
      345313,
      345523,
      323452,
      275026,
      341508,
      323524,
      323525,
      313741,
      310104,
      341261,
      318046,
      298744
    ]
  },
  {
    "_id": "67729c7abc9e10b44b7d0507",
    "vid": 14,
    "tid": 413156,
    "badge": "https://lain.bgm.tv/pic/photo/l/32/c1/437960_T2Mmm.jpg",
    "note": "本文已收录于「半月刊Dec2024下」",
    "blogs": [
      346351,
      346043,
      345884,
      309522,
      309461,
      310629,
      345037,
      346440,
      345653,
      31940,
      31139,
      31140
    ]
  },
  {
    "_id": "678c624c87115eef85b7a86e",
    "vid": 15,
    "tid": 414475,
    "badge": "https://lain.bgm.tv/pic/photo/l/32/c1/437960_maOO9.jpg",
    "note": "本文已收录于「半月刊Jan2025上」",
    "blogs": [
      343502,
      344643,
      347804,
      346438,
      291137,
      307246,
      270913,
      271929,
      292610,
      308874,
      298233,
      343733,
      344576
    ]
  },
  {
    "_id": "67bea55017ad3dc4c0dba395",
    "vid": 16,
    "tid": 417449,
    "badge": "https://lain.bgm.tv/pic/photo/l/32/c1/437960_maOO9.jpg",
    "note": "本文已收录于「半月刊Feb2025下」",
    "blogs": [
      278518,
      312359,
      299380,
      321199,
      337178,
      307479,
      330103,
      307633,
      341087,
      310804,
      306137,
      342729
    ]
  },
  {
    "_id": "68b5314f9784104e7bdb1bc2",
    "vid": 17,
    "tid": 429281,
    "badge": "https://lain.bgm.tv/pic/photo/l/32/c1/437960_maOO9.jpg",
    "note": "本文已收录于「半月刊Jul2025下」",
    "blogs": [
      308839,
      79,
      281372,
      300732,
      345559,
      325139,
      345324,
      345328,
      345982,
      333742
    ]
  },
  {
    "_id": "68b531ce9784104e7bdb1bc5",
    "vid": 18,
    "tid": 430825,
    "badge": "https://lain.bgm.tv/pic/photo/l/32/c1/437960_maOO9.jpg",
    "note": "本文已收录于「半月刊Aug2025上」",
    "blogs": [
      337683,
      337688,
      337899,
      355140,
      345581,
      339222,
      280150,
      345777,
      271796,
      308336,
      341215,
      341335
    ]
  },
  {
    "_id": "68b532279784104e7bdb1bc8",
    "vid": 19,
    "tid": 432006,
    "badge": "https://lain.bgm.tv/pic/photo/l/32/c1/437960_maOO9.jpg",
    "note": "本文已收录于「半月刊Aug2025下」",
    "blogs": [
      337683,
      350740,
      345256,
      313901,
      356890,
      357374,
      356750,
      352871,
      350856,
      296546,
      348807,
      293438,
      355398
    ]
  }
]